supernest/__init__.py
supernest/core.py
supernest/utils.py
supernest/framework/__init__.py
supernest/framework/gaussian_models.py
supernest/framework/mixtures.py
supernest/framework/offset_model.py
supernest/framework/polychord.py
supernest/proposals/__init__.py
supernest/proposals/gaussian.py
supernest/proposals/truncated_gaussian.py
supernest/proposals/types.py
supernest/tests/__init__.py
supernest/tests/check_cosmology.py
supernest/tests/check_proposal.py
supernest/tests/plot.py
supernest/tests/test_cosmology.py
supernest/tests/test_exceptions.py
supernest/tests/test_proposal.py
supernest/tests/test_superposition.py
supernest/tests/test_typing.py
supernest-3.4.0.dist-info/LICENSE
supernest-3.4.0.dist-info/METADATA
supernest-3.4.0.dist-info/WHEEL
supernest-3.4.0.dist-info/top_level.txt
supernest-3.4.0.dist-info/RECORD
