Metadata-Version: 2.1
Name: supernest
Version: 3.4.0
Summary: A wrapper for use of SSPR in nested sampling packages such as PolyChord and Multinest
Home-page: https://gitlab.com/a-p-petrosyan/sspr
Author: Aleksandr Petrosyan
Author-email: a-p-petrosyan@yandex.ru
License: LGPLv3
Platform: UNKNOWN
Classifier: License :: OSI Approved :: GNU Lesser General Public License v3 (LGPLv3)
Requires-Python: >=3.6
License-File: LICENSE
Requires-Dist: anesthetic
Requires-Dist: numpy
Requires-Dist: matplotlib
